s3client
